wgs_correction/__init__.py
wgs_correction-0.1.0.dist-info/METADATA
wgs_correction-0.1.0.dist-info/WHEEL
wgs_correction-0.1.0.dist-info/RECORD
